[{"Title":"मकान मालकिन की चूत चोदी जुगाड़ से","author":"रॉनी6","date":"03-03-2022","views":"235,855","description":"सेक्सी पड़ोसन की चुदाई की मैंने! वो मेरी मकान मालकिन थी. गदर माल भाभी की चूचियां अति विशाल थी. मैंने कैसे जुगाड़ किया भाभी की चूत मारने का?","href":"https://www.freesexkahani.com/bhabhi-sex/sexy-padosan-ki-chudai/","tags":["Padosi"]},{"Title":"शादीशुदा जोड़े की संतानोत्पत्ति में मदद की- 1","author":"अनिकेत भारद्वाज","date":"04-03-2022","views":"180,411","description":"देसी भाबी सेक्स कहानी में पढ़ें कि एक कपल को बच्चा नहीं हो रहा था. उन्होंने मुझसे सम्पर्क किया तो मैंने अपने सामने उन दोनों को सेक्स करने को कहा.","href":"https://www.freesexkahani.com/antarvasna/desi-bhabi-sex/","tags":["Desi Bhabhi Sex","Gandi Kahani","Hot girl","Nangi Ladki","Wife Sex"]},{"Title":"पापा ने दीदी को मेरे सामने चोदा","author":"सिम्पल बॉय","date":"03-03-2022","views":"401,495","description":"बाप बेटी चुदाई कहानी मेरे सौतेले पापा और मेरी सगी बहन के सेक्स की है. ये पूरा काण्ड मेरे सामने हुआ. मेरी दीदी बहुत बड़ी चालू माल थी. ","href":"https://www.freesexkahani.com/family-sex-stories/baap-beti-chudai/","tags":["Bhai Behan Ki Chudai","Desi Ladki","Gandi Kahani","Hot girl","Hotel Sex","Oral Sex","Porn story in Hindi"]},{"Title":"सेक्सी विधवा मैडम की चूत में ड्राइवर का लंड","author":"दिल्ली बॉय","date":"02-03-2022","views":"216,940","description":"इस ड्राईवर सेक्स कहानी में पढ़ें कि एक विधवा अमीर लड़की सेक्स की प्यासी थी. उसका यार भी उसकी प्यास नहीं बुझा पाया तो उसने अपने ड्राईवर को उकसाया.","href":"https://www.freesexkahani.com/xxx-kahani/widow-lady-driver-sex/","tags":["Gand Ki Chudai","Hot girl","Hot Sex Stories","Kamvasna","Nangi Ladki","Oral Sex"]},{"Title":"बिल्डिंग की छत पर खोली गर्लफ्रेंड की सील","author":"फरियाज पटेल","date":"02-03-2022","views":"175,006","description":"देसी गर्लफ्रेंड सेक्सी कहानी मेरी बिल्डिंग में ही रहने वाली लड़की की चुदाई की है। मैंने उसको गर्लफ्रेंड बनाकर चुदाई के लिए पटाया और एक रात छत पर बुला लिया.","href":"https://www.freesexkahani.com/first-time-sex/desi-girlfriend-sexy-kahani/","tags":["Bur Ki Chudai","College Girl","Desi Ladki","Kamvasna","Oral Sex","public sex","Sex With Girlfriend"]},{"Title":"प्राध्यापिका ने अपने छात्र से चुदाई करवा ली","author":"पंकज टॉप","date":"01-03-2022","views":"352,788","description":"हस्बैंड वाइफ चीटिंग सेक्स कहानी एक टीचर की है. उसने अपने शौहर को दूसरी लड़की के साथ सेक्स करते देखा तो बदला लेने के लिए उसने एक लड़के से चुदाई कर ली.","href":"https://www.freesexkahani.com/teacher-sex/husband-wife-cheating-sex-kahani/","tags":["Audio Sex Story","Chudai Ki Kahani","Garam Kahani","Kamvasna","Sex With Girlfriend","Wife Sex"]},{"Title":"सड़क पर लड़की को पटाकर घर में चोद दिया","author":"सचिन जाट","date":"01-03-2022","views":"129,613","description":"बुर की चुदाई हिंदी में पढ़ें कि कैसे मैंने सडक पर एक लड़की देखी और वो मुझे पसंद आ गयी. उसके बाद मैंने उसे कैसे पटाया और कैसे उसको अपने घर बुलाकर चोदा.","href":"https://www.freesexkahani.com/teenage-girl/bur-ki-chudai-hindi-mein/","tags":["Bur Ki Chudai","Gand Ki Chudai","Hot girl","Nangi Ladki","Oral Sex","Sex With Girlfriend"]},{"Title":"फुफेरी बहन की रात भर चुत चुदाई- 2","author":"अरुण नहन","date":"28-02-2022","views":"305,948","description":"हॉट सेक्स विद कज़िन सिस्टर का मजा मुझे मिला मेरी बुआ की जवान बेटी के साथ. वो हमारे घर में थी जब हमारी सेटिंग हो गयी. यह हमारा पहला सेक्स था.","href":"https://www.freesexkahani.com/first-time-sex/hot-sex-with-cousin-sister/","tags":["Bhai Behan Ki Chudai","Bur Ki Chudai","Desi Ladki","Hindi Sex Kahani","Hot girl","Nangi Ladki","Oral Sex"]},{"Title":"गर्म साली की चुदाई का मजा ले ही लिया- 2","author":"बादल गार्गी","date":"28-02-2022","views":"194,204","description":"इंडियन जीजा साली Xxx कहानी में पढ़ें कि मेरा साली मुझसे चुदना चाहती थी पर गर्भ से डरती थी. वो मेरा लंड चूस कर मजा देती थी. वो चुदी शादी के बाद!","href":"https://www.freesexkahani.com/sali-sex/indian-jija-sali-xxx-kahani/","tags":["Desi Ladki","Hot girl","Kamukta","Mastram Sex Story","Nangi Ladki","Oral Sex"]},{"Title":"फुफेरी बहन की रात भर चुत चुदाई- 1","author":"अरुण नहन","date":"27-02-2022","views":"394,683","description":"ब्रदर एंड सिस्टर सेक्सी कहानी मेरी बुआ की जवान बेटी की है. वो कुछ दिन हमारे घर रही तो मेरी नजर ना चाहते हुए भी उसके गर्म जिस्म पर टिक जाती थी.","href":"https://www.freesexkahani.com/antarvasna/brother-and-sister-sexy-kahani/","tags":["College Girl","Desi Ladki","Garam Kahani","Hindi Sexy Story","Kamvasna"]}]